atomic_search/__init__.py
atomic_search/atomic_search.py
atomic_search/extract_atoms.py
atomic_search/form_molecule.py
atomic_search-0.1.0.dist-info/LICENSE
atomic_search-0.1.0.dist-info/METADATA
atomic_search-0.1.0.dist-info/WHEEL
atomic_search-0.1.0.dist-info/top_level.txt
atomic_search-0.1.0.dist-info/RECORD
