Metadata-Version: 2.1
Name: atomic-search
Version: 0.1.0
Summary: A Python package for extracting and detecting malicious JavaScript syntax through atomic and molecule search.
Home-page: https://github.com/aflinxh/atomic_search
Author: Alfin Gusti Alamsyah
Author-email: Alfin Gusti Alamsyah <alfinalamsyahhh@gmail.com>
License: MIT
Project-URL: Homepage, https://github.com/aflinxh/atomic_search
Project-URL: Documentation, https://github.com/aflinxh/atomic_search
Project-URL: Issues, https://github.com/Aflinxh/atomic_search/issues
Keywords: malicious code detection,JavaScript analysis,obfuscation,feature extraction
Classifier: Programming Language :: Python :: 3
Classifier: License :: OSI Approved :: MIT License
Classifier: Operating System :: OS Independent
Classifier: Intended Audience :: Developers
Classifier: Intended Audience :: Science/Research
Classifier: Topic :: Software Development :: Libraries :: Python Modules
Classifier: Topic :: Security
Classifier: Topic :: Software Development :: Libraries :: Application Frameworks
Requires-Python: >=3.7
License-File: LICENSE
Provides-Extra: dev
Requires-Dist: pytest>=8.3.3; extra == "dev"
Requires-Dist: invoke>=2.2.0; extra == "dev"
Provides-Extra: dynamic
Requires-Dist: optional-dependencies; extra == "dynamic"
